forecast_verifier/__init__.py
forecast_verifier/__version__.py
forecast_verifier/dataset.py
forecast_verifier/graph.py
forecast_verifier/metrics.py
forecast_verifier/model.py
forecast_verifier/utils.py
forecast_verifier/verifier.py
forecast_verifier-0.1.2.dist-info/METADATA
forecast_verifier-0.1.2.dist-info/WHEEL
forecast_verifier-0.1.2.dist-info/licenses/LICENSE.txt
forecast_verifier-0.1.2.dist-info/RECORD
