Metadata-Version: 2.4
Name: forecast_verifier
Version: 0.1.2
Summary: Verify causal graph from data-driven models
Author-email: Chi Bui <thimaichi.bui@student.kuleuven.be>
License: MIT
License-File: LICENSE.txt
Classifier: License :: OSI Approved :: MIT License
Classifier: Programming Language :: Python :: 3
Requires-Python: >=3.9
Requires-Dist: graphviz>=0.21
Requires-Dist: numpy>=1.0.0
Requires-Dist: pandas>=1.0.0
Requires-Dist: scikit-learn>=1.3.0
Requires-Dist: spicy
